skstorsosim/__init__.py
skstorsosim/_version.py
skstorsosim/empty.py
scikit_surgerytorsosimulator-0.0.6.1.dist-info/LICENSE
scikit_surgerytorsosimulator-0.0.6.1.dist-info/METADATA
scikit_surgerytorsosimulator-0.0.6.1.dist-info/WHEEL
scikit_surgerytorsosimulator-0.0.6.1.dist-info/entry_points.txt
scikit_surgerytorsosimulator-0.0.6.1.dist-info/top_level.txt
scikit_surgerytorsosimulator-0.0.6.1.dist-info/RECORD
